i3lockfab.py
i3lockfab-0.0.3.dist-info/METADATA
i3lockfab-0.0.3.dist-info/WHEEL
i3lockfab-0.0.3.dist-info/entry_points.txt
i3lockfab-0.0.3.dist-info/top_level.txt
i3lockfab-0.0.3.dist-info/RECORD
